colorsfuto/__init__.py
colorsfuto-0.1.dist-info/METADATA
colorsfuto-0.1.dist-info/WHEEL
colorsfuto-0.1.dist-info/top_level.txt
colorsfuto-0.1.dist-info/RECORD
