Metadata-Version: 2.1
Name: colorsfuto
Version: 0.1
Summary: Un Module qui permets de multiplier Les Couleurs en Python
Home-page: UNKNOWN
Author: colorsfuto
Author-email: colorsfuto@gmail.com
License: UNKNOWN
Platform: UNKNOWN
Classifier: Programming Language :: Python :: 3
Classifier: License :: OSI Approved :: MIT License
Classifier: Operating System :: OS Independent
